residential_proxy_sdk/__init__.py
residential_proxy_sdk/main.py
residential_proxy_sdk-0.1.8.dist-info/METADATA
residential_proxy_sdk-0.1.8.dist-info/WHEEL
residential_proxy_sdk-0.1.8.dist-info/top_level.txt
residential_proxy_sdk-0.1.8.dist-info/RECORD
