Metadata-Version: 2.1
Name: residential-proxy-sdk
Version: 0.1.8
Summary: A proxy SDK for managing rotating residential proxies in Vietnam
Home-page: https://vinproxy.net
Author: Ghant Hoang
Author-email: thaithang115@gmail.com
License: UNKNOWN
Project-URL: Source Code, https://github.com/residential-proxy/residential-proxy-python
Platform: UNKNOWN
Classifier: Programming Language :: Python :: 3
Classifier: License :: OSI Approved :: MIT License
Classifier: Operating System :: OS Independent
Requires-Python: >=3.6
Requires-Dist: requests
